pokerkit/__init__.py
pokerkit/analysis.py
pokerkit/games.py
pokerkit/hands.py
pokerkit/lookups.py
pokerkit/notation.py
pokerkit/py.typed
pokerkit/state.py
pokerkit/utilities.py
pokerkit/tests/__init__.py
pokerkit/tests/test_analysis.py
pokerkit/tests/test_games.py
pokerkit/tests/test_lookups.py
pokerkit/tests/test_notation.py
pokerkit/tests/test_papers.py
pokerkit/tests/test_rules.py
pokerkit/tests/test_state.py
pokerkit/tests/test_utilities.py
pokerkit/tests/test_wsop/__init__.py
pokerkit/tests/test_wsop/test_2023_43_5.py
pokerkit/tests/test_wsop/test_2023_54_4.py
pokerkit-0.7.0.dist-info/licenses/LICENSE
pokerkit-0.7.0.dist-info/METADATA
pokerkit-0.7.0.dist-info/WHEEL
pokerkit-0.7.0.dist-info/top_level.txt
pokerkit-0.7.0.dist-info/RECORD
