Metadata-Version: 2.4
Name: pokerkit
Version: 0.7.0
Summary: An open-source Python library for poker game simulations, hand evaluations, and statistical analysis
Home-page: https://github.com/uoftcprg/pokerkit
Author: Universal, Open, Free, and Transparent Computer Poker Research Group
Author-email: juhok@andrew.cmu.edu
License: MIT
Project-URL: Documentation, https://pokerkit.readthedocs.io/en/latest/
Project-URL: Source, https://github.com/uoftcprg/pokerkit
Project-URL: Tracker, https://github.com/uoftcprg/pokerkit/issues
Keywords: artificial-intelligence,deep-learning,game,game-development,game-theory,holdem-poker,imperfect-information-game,libratus,pluribus,poker,poker-engine,poker-evaluator,poker-game,poker-hands,poker-library,poker-strategies,python,reinforcement-learning,texas-holdem
Classifier: Development Status :: 5 - Production/Stable
Classifier: Intended Audience :: Developers
Classifier: Intended Audience :: Education
Classifier: Topic :: Education
Classifier: Topic :: Games/Entertainment
Classifier: Topic :: Games/Entertainment :: Board Games
Classifier: Topic :: Scientific/Engineering
Classifier: Topic :: Scientific/Engineering :: Artificial Intelligence
Classifier: License :: OSI Approved :: MIT License
Classifier: Operating System :: OS Independent
Classifier: Programming Language :: Python
Classifier: Programming Language :: Python :: 3
Classifier: Programming Language :: Python :: 3 :: Only
Classifier: Programming Language :: Python :: 3.11
Classifier: Programming Language :: Python :: 3.12
Classifier: Programming Language :: Python :: 3.13
Requires-Python: >=3.11
License-File: LICENSE
Dynamic: author
Dynamic: author-email
Dynamic: classifier
Dynamic: description
Dynamic: description-content-type
Dynamic: home-page
Dynamic: keywords
Dynamic: license
Dynamic: license-file
Dynamic: project-url
Dynamic: requires-python
Dynamic: summary
